gateway_defender/__init__.py
gateway_defender/admin.py
gateway_defender/apps.py
gateway_defender/custom_decorator.py
gateway_defender/models.py
gateway_defender/tests.py
gateway_defender/urls.py
gateway_defender/views.py
gateway_defender/commands/create_fake_authenticated_user.py
gateway_defender/management/commands/create_fake_authenticated_user.py
gateway_defender/migrations/0001_initial.py
gateway_defender/migrations/0002_auto_20210529_2306.py
gateway_defender/migrations/0003_authtoggle_timeout.py
gateway_defender/migrations/0004_alter_authtoggle_timeout.py
gateway_defender/migrations/0005_rename_enable_protection_authtoggle_on.py
gateway_defender/migrations/0006_rename_on_authtoggle_protected.py
gateway_defender/migrations/0007_rename_protected_authtoggle_is_protected.py
gateway_defender/migrations/0008_rename_swap_html_authtoggle_faravahar.py
gateway_defender/migrations/0009_authtoggle_email.py
gateway_defender/migrations/__init__.py
gateway_defender/migrations/__pycache__/0001_initial.cpython-313.pyc
gateway_defender/migrations/__pycache__/0002_auto_20210529_2306.cpython-313.pyc
gateway_defender/migrations/__pycache__/0003_authtoggle_timeout.cpython-313.pyc
gateway_defender/migrations/__pycache__/0004_alter_authtoggle_timeout.cpython-313.pyc
gateway_defender/migrations/__pycache__/0005_rename_enable_protection_authtoggle_on.cpython-313.pyc
gateway_defender/migrations/__pycache__/0006_rename_on_authtoggle_protected.cpython-313.pyc
gateway_defender/migrations/__pycache__/0007_rename_protected_authtoggle_is_protected.cpython-313.pyc
gateway_defender/migrations/__pycache__/0008_rename_swap_html_authtoggle_faravahar.cpython-313.pyc
gateway_defender/migrations/__pycache__/0009_authtoggle_email.cpython-313.pyc
gateway_defender/migrations/__pycache__/__init__.cpython-313.pyc
gateway_defender/static/css/gateway.css
gateway_defender/static/img/crimson-hexagram.ico
gateway_defender/static/img/wings-white-cropped.png
gateway_defender-0.1.3.dist-info/METADATA
gateway_defender-0.1.3.dist-info/WHEEL
gateway_defender-0.1.3.dist-info/top_level.txt
gateway_defender-0.1.3.dist-info/RECORD
