Metadata-Version: 2.4
Name: gateway-defender
Version: 0.1.3
Summary: Reusable Django app gateway-defender
Author-email: Muhammad Rabi Uddin <rabiuddin1@gmail.com>
License: MIT License
Keywords: django,gateway_-defender,gateway_defender,authentication,users
Classifier: Framework :: Django
Classifier: Programming Language :: Python :: 3
Classifier: License :: OSI Approved :: MIT License
Classifier: Operating System :: OS Independent
Requires-Python: >=3.8
Requires-Dist: Django<7,>=4.2
